eidreader.py
eidreader-1.0.8.dist-info/METADATA
eidreader-1.0.8.dist-info/WHEEL
eidreader-1.0.8.dist-info/entry_points.txt
eidreader-1.0.8.dist-info/licenses/COPYING
eidreader-1.0.8.dist-info/RECORD
