Metadata-Version: 2.3
Name: eidreader
Version: 1.0.8
Summary: Read data from Belgian eId card via command-line
Project-URL: Homepage, https://eidreader.lino-framework.org
Project-URL: Repository, https://github.com/lino-framework/eidreader
Author-email: Rumma & Ko Ltd <info@lino-framework.org>, Luc Saffre <luc@lino-framework.org>
License:                     GNU AFFERO GENERAL PUBLIC LICENSE
License-File: COPYING
Classifier: Development Status :: 5 - Production/Stable
Classifier: Intended Audience :: Developers
Classifier: License :: OSI Approved :: GNU Affero General Public License v3
Classifier: Natural Language :: English
Classifier: Operating System :: OS Independent
Classifier: Programming Language :: Python
Classifier: Programming Language :: Python :: 3
Requires-Dist: pykcs11
Requires-Dist: requests
